{
  "date": "2026-01-30",
  "lastUpdated": "04:54 AM, 30 January 2026",
  "shows": [
    {
      "movie_id": "TrAcSfZv4oSLw47hzBudCQ",
      "movie_name": "Aa Bata Aama",
      "show_id": "61105:ini-lotse-ktm",
      "venue": "ini-lotse-ktm",
      "theatre": "iNi Cinemas Lotse - Audi 1",
      "date": "2026-01-30T07:45:00+05:45",
      "time": "",
      "seats": 240,
      "sold": 3,
      "reserved": 0,
      "available": 237,
      "gross": 600,
      "occupancy_percent": 1.25
    },
    {
      "movie_id": "TrAcSfZv4oSLw47hzBudCQ",
      "movie_name": "Aa Bata Aama",
      "show_id": "38924:ranjana-cineplex",
      "venue": "ranjana-cineplex",
      "theatre": "Ranjana Cineplex - Audi - 3",
      "date": "2026-01-30T08:00:00+05:45",
      "time": "",
      "seats": 164,
      "sold": 2,
      "reserved": 45,
      "available": 117,
      "gross": 9400,
      "occupancy_percent": 28.66
    },
    {
      "movie_id": "TrAcSfZv4oSLw47hzBudCQ",
      "movie_name": "Aa Bata Aama",
      "show_id": "61115:ini-cinemas-nb-center",
      "venue": "ini-cinemas-nb-center",
      "theatre": "iNi Cinemas NB Center - Audi -1 (DTS: X)",
      "date": "2026-01-30T07:45:00+05:45",
      "time": "",
      "seats": 177,
      "sold": 2,
      "reserved": 2,
      "available": 173,
      "gross": 900,
      "occupancy_percent": 2.26
    },
    {
      "movie_id": "TrAcSfZv4oSLw47hzBudCQ",
      "movie_name": "Aa Bata Aama",
      "show_id": "46356:bsr-movies",
      "venue": "bsr-movies",
      "theatre": "BSR Movies - Atmos 2",
      "date": "2026-01-30T08:00:00+05:45",
      "time": "",
      "seats": 180,
      "sold": 4,
      "reserved": 15,
      "available": 161,
      "gross": 3800,
      "occupancy_percent": 10.56
    },
    {
      "movie_id": "TrAcSfZv4oSLw47hzBudCQ",
      "movie_name": "Aa Bata Aama",
      "show_id": "11493:infinity-movies",
      "venue": "infinity-movies",
      "theatre": "Infinity Movies - Audi 1",
      "date": "2026-01-30T08:00:00+05:45",
      "time": "",
      "seats": 181,
      "sold": 4,
      "reserved": 3,
      "available": 174,
      "gross": 1050,
      "occupancy_percent": 3.87
    },
    {
      "movie_id": "TrAcSfZv4oSLw47hzBudCQ",
      "movie_name": "Aa Bata Aama",
      "show_id": "3297:kirtipur-cineplex",
      "venue": "kirtipur-cineplex",
      "theatre": "Kirtipur Cineplex - Audi-1",
      "date": "2026-01-30T08:00:00+05:45",
      "time": "",
      "seats": 285,
      "sold": 161,
      "reserved": 35,
      "available": 89,
      "gross": 29400,
      "occupancy_percent": 68.77
    },
    {
      "movie_id": "TrAcSfZv4oSLw47hzBudCQ",
      "movie_name": "Aa Bata Aama",
      "show_id": "61124:ini-qbox-butwal",
      "venue": "ini-qbox-butwal",
      "theatre": "iNi Cinemas QBox - Audi 1",
      "date": "2026-01-30T07:45:00+05:45",
      "time": "",
      "seats": 196,
      "sold": 8,
      "reserved": 2,
      "available": 186,
      "gross": 1650,
      "occupancy_percent": 5.1
    },
    {
      "movie_id": "TrAcSfZv4oSLw47hzBudCQ",
      "movie_name": "Aa Bata Aama",
      "show_id": "154442:qfx-butwal",
      "venue": "qfx-butwal",
      "theatre": "QFX Butwal - AUDI 2",
      "date": "2026-01-30T08:00:00+05:45",
      "time": "",
      "seats": 196,
      "sold": 44,
      "reserved": 0,
      "available": 152,
      "gross": 7260,
      "occupancy_percent": 22.45
    },
    {
      "movie_id": "TrAcSfZv4oSLw47hzBudCQ",
      "movie_name": "Aa Bata Aama",
      "show_id": "24842:one-cinemas-new-baneshwor",
      "venue": "one-cinemas-new-baneshwor",
      "theatre": "One Cinemas New Baneshwor - Audi 1",
      "date": "2026-01-30T08:00:00+05:45",
      "time": "",
      "seats": 208,
      "sold": 19,
      "reserved": 0,
      "available": 189,
      "gross": 4750,
      "occupancy_percent": 9.13
    },
    {
      "movie_id": "TrAcSfZv4oSLw47hzBudCQ",
      "movie_name": "Aa Bata Aama",
      "show_id": "61146:bishwojyoti-cineplex",
      "venue": "bishwojyoti-cineplex",
      "theatre": "iNi Cinemas - Bishwojyoti - Audi 2",
      "date": "2026-01-30T07:45:00+05:45",
      "time": "",
      "seats": 89,
      "sold": 4,
      "reserved": 0,
      "available": 85,
      "gross": 700,
      "occupancy_percent": 4.49
    },
    {
      "movie_id": "TrAcSfZv4oSLw47hzBudCQ",
      "movie_name": "Aa Bata Aama",
      "show_id": "154472:qfx-bhaktapur",
      "venue": "qfx-bhaktapur",
      "theatre": "QFX Bhaktapur - AUDI 3",
      "date": "2026-01-30T08:00:00+05:45",
      "time": "",
      "seats": 247,
      "sold": 62,
      "reserved": 0,
      "available": 185,
      "gross": 13640,
      "occupancy_percent": 25.1
    },
    {
      "movie_id": "FrHBK8fhAKYd7cNZXaAHpK",
      "movie_name": "Primate",
      "show_id": "61129:ini-qbox-butwal",
      "venue": "ini-qbox-butwal",
      "theatre": "iNi Cinemas QBox - Audi 2",
      "date": "2026-01-30T07:30:00+05:45",
      "time": "",
      "seats": 196,
      "sold": 0,
      "reserved": 1,
      "available": 195,
      "gross": 165,
      "occupancy_percent": 0.51
    },
    {
      "movie_id": "FrHBK8fhAKYd7cNZXaAHpK",
      "movie_name": "Primate",
      "show_id": "61141:bishwojyoti-cineplex",
      "venue": "bishwojyoti-cineplex",
      "theatre": "iNi Cinemas - Bishwojyoti - Audi 1",
      "date": "2026-01-30T07:30:00+05:45",
      "time": "",
      "seats": 201,
      "sold": 4,
      "reserved": 0,
      "available": 197,
      "gross": 700,
      "occupancy_percent": 1.99
    },
    {
      "movie_id": "FrHBK8fhAKYd7cNZXaAHpK",
      "movie_name": "Primate",
      "show_id": "61110:ini-lotse-ktm",
      "venue": "ini-lotse-ktm",
      "theatre": "iNi Cinemas Lotse - Audi 2",
      "date": "2026-01-30T07:30:00+05:45",
      "time": "",
      "seats": 240,
      "sold": 0,
      "reserved": 0,
      "available": 240,
      "gross": 0,
      "occupancy_percent": 0.0
    },
    {
      "movie_id": "FrHBK8fhAKYd7cNZXaAHpK",
      "movie_name": "Primate",
      "show_id": "122476:cdc-cinemas",
      "venue": "cdc-cinemas",
      "theatre": "CDC Cinemas - Cine Dine",
      "date": "2026-01-30T07:30:00+05:45",
      "time": "",
      "seats": 60,
      "sold": 0,
      "reserved": 7,
      "available": 53,
      "gross": 2800,
      "occupancy_percent": 11.67
    },
    {
      "movie_id": "ZNZDtMxLPD73QZKmNaNM4A",
      "movie_name": "Border 2",
      "show_id": "154367:qfx-labim",
      "venue": "qfx-labim",
      "theatre": "QFX Labim - AUDI 2",
      "date": "2026-01-30T08:00:00+05:45",
      "time": "",
      "seats": 180,
      "sold": 21,
      "reserved": 0,
      "available": 159,
      "gross": 5880,
      "occupancy_percent": 11.67
    }
  ]
}