[
  {
    "movie_id": "zDquhoHrfUHpyVzquamLCN",
    "movie_name": "Dhurandhar - The Revenge",
    "total_shows": 243,
    "seats": 48406,
    "sold": 1974,
    "reserved": 1340,
    "available": 45092,
    "housefull": 0,
    "fastfilling": 2,
    "venues": [
      {
        "venue": "qfx-labim",
        "total_shows": 10,
        "seats": 1815,
        "sold": 457,
        "reserved": 140,
        "available": 1218,
        "housefull": 0,
        "fastfilling": 0
      },
      {
        "venue": "big-movies",
        "total_shows": 11,
        "seats": 3322,
        "sold": 159,
        "reserved": 534,
        "available": 2629,
        "housefull": 0,
        "fastfilling": 0
      },
      {
        "venue": "qfx-civil",
        "total_shows": 10,
        "seats": 3630,
        "sold": 130,
        "reserved": 4,
        "available": 3496,
        "housefull": 0,
        "fastfilling": 0
      },
      {
        "venue": "qfx-chhaya",
        "total_shows": 9,
        "seats": 1154,
        "sold": 84,
        "reserved": 0,
        "available": 1070,
        "housefull": 0,
        "fastfilling": 0
      },
      {
        "venue": "qfx-durbar",
        "total_shows": 7,
        "seats": 363,
        "sold": 118,
        "reserved": 11,
        "available": 234,
        "housefull": 0,
        "fastfilling": 2
      },
      {
        "venue": "ini-lotse-ktm",
        "total_shows": 6,
        "seats": 1440,
        "sold": 2,
        "reserved": 0,
        "available": 1438,
        "housefull": 0,
        "fastfilling": 0
      },
      {
        "venue": "ini-cinemas-nb-center",
        "total_shows": 6,
        "seats": 1194,
        "sold": 10,
        "reserved": 0,
        "available": 1184,
        "housefull": 0,
        "fastfilling": 0
      },
      {
        "venue": "one-cinemas-new-baneshwor",
        "total_shows": 10,
        "seats": 1778,
        "sold": 208,
        "reserved": 6,
        "available": 1564,
        "housefull": 0,
        "fastfilling": 0
      },
      {
        "venue": "fcube",
        "total_shows": 10,
        "seats": 2072,
        "sold": 40,
        "reserved": 236,
        "available": 1796,
        "housefull": 0,
        "fastfilling": 0
      },
      {
        "venue": "ranjana-cineplex",
        "total_shows": 10,
        "seats": 1896,
        "sold": 6,
        "reserved": 6,
        "available": 1884,
        "housefull": 0,
        "fastfilling": 0
      },
      {
        "venue": "kirtipur-cineplex",
        "total_shows": 6,
        "seats": 1158,
        "sold": 16,
        "reserved": 0,
        "available": 1142,
        "housefull": 0,
        "fastfilling": 0
      },
      {
        "venue": "qfx-square-mall",
        "total_shows": 9,
        "seats": 1507,
        "sold": 66,
        "reserved": 0,
        "available": 1441,
        "housefull": 0,
        "fastfilling": 0
      },
      {
        "venue": "bsr-movies",
        "total_shows": 6,
        "seats": 1128,
        "sold": 7,
        "reserved": 94,
        "available": 1027,
        "housefull": 0,
        "fastfilling": 0
      },
      {
        "venue": "qs-cinemas",
        "total_shows": 7,
        "seats": 1115,
        "sold": 60,
        "reserved": 0,
        "available": 1055,
        "housefull": 0,
        "fastfilling": 0
      },
      {
        "venue": "bishwojyoti-cineplex",
        "total_shows": 6,
        "seats": 982,
        "sold": 0,
        "reserved": 0,
        "available": 982,
        "housefull": 0,
        "fastfilling": 0
      },
      {
        "venue": "one-cinemas-kalimati",
        "total_shows": 6,
        "seats": 861,
        "sold": 92,
        "reserved": 1,
        "available": 768,
        "housefull": 0,
        "fastfilling": 0
      },
      {
        "venue": "qfx-bhaktapur",
        "total_shows": 10,
        "seats": 2354,
        "sold": 191,
        "reserved": 133,
        "available": 2030,
        "housefull": 0,
        "fastfilling": 0
      },
      {
        "venue": "pokhara-cineplex",
        "total_shows": 6,
        "seats": 1830,
        "sold": 16,
        "reserved": 0,
        "available": 1814,
        "housefull": 0,
        "fastfilling": 0
      },
      {
        "venue": "qfx-jalma",
        "total_shows": 6,
        "seats": 1599,
        "sold": 28,
        "reserved": 0,
        "available": 1571,
        "housefull": 0,
        "fastfilling": 0
      },
      {
        "venue": "chitwan-cineplex",
        "total_shows": 6,
        "seats": 1162,
        "sold": 37,
        "reserved": 2,
        "available": 1123,
        "housefull": 0,
        "fastfilling": 0
      },
      {
        "venue": "qfx-skyline",
        "total_shows": 8,
        "seats": 1015,
        "sold": 85,
        "reserved": 12,
        "available": 918,
        "housefull": 0,
        "fastfilling": 0
      },
      {
        "venue": "ini-simara",
        "total_shows": 5,
        "seats": 833,
        "sold": 0,
        "reserved": 0,
        "available": 833,
        "housefull": 0,
        "fastfilling": 0
      },
      {
        "venue": "ini-qbox-butwal",
        "total_shows": 6,
        "seats": 1176,
        "sold": 21,
        "reserved": 0,
        "available": 1155,
        "housefull": 0,
        "fastfilling": 0
      },
      {
        "venue": "qfx-butwal",
        "total_shows": 6,
        "seats": 1136,
        "sold": 51,
        "reserved": 116,
        "available": 969,
        "housefull": 0,
        "fastfilling": 0
      },
      {
        "venue": "qfx-apex-mall",
        "total_shows": 3,
        "seats": 600,
        "sold": 0,
        "reserved": 0,
        "available": 600,
        "housefull": 0,
        "fastfilling": 0
      },
      {
        "venue": "qfx-bageshwori",
        "total_shows": 7,
        "seats": 2024,
        "sold": 5,
        "reserved": 0,
        "available": 2019,
        "housefull": 0,
        "fastfilling": 0
      },
      {
        "venue": "cineroyale",
        "total_shows": 10,
        "seats": 1988,
        "sold": 0,
        "reserved": 0,
        "available": 1988,
        "housefull": 0,
        "fastfilling": 0
      },
      {
        "venue": "qfx-one-stop-mall",
        "total_shows": 6,
        "seats": 813,
        "sold": 72,
        "reserved": 0,
        "available": 741,
        "housefull": 0,
        "fastfilling": 0
      },
      {
        "venue": "qfx-cineflix-itahari",
        "total_shows": 7,
        "seats": 938,
        "sold": 11,
        "reserved": 2,
        "available": 925,
        "housefull": 0,
        "fastfilling": 0
      },
      {
        "venue": "pathivara-cine-plaza",
        "total_shows": 4,
        "seats": 916,
        "sold": 0,
        "reserved": 0,
        "available": 916,
        "housefull": 0,
        "fastfilling": 0
      },
      {
        "venue": "elite-cinemas",
        "total_shows": 5,
        "seats": 928,
        "sold": 2,
        "reserved": 40,
        "available": 886,
        "housefull": 0,
        "fastfilling": 0
      },
      {
        "venue": "suvakamna-cinemas",
        "total_shows": 2,
        "seats": 380,
        "sold": 0,
        "reserved": 0,
        "available": 380,
        "housefull": 0,
        "fastfilling": 0
      },
      {
        "venue": "cdc-cinemas",
        "total_shows": 6,
        "seats": 687,
        "sold": 0,
        "reserved": 0,
        "available": 687,
        "housefull": 0,
        "fastfilling": 0
      },
      {
        "venue": "omax-cinema",
        "total_shows": 2,
        "seats": 756,
        "sold": 0,
        "reserved": 0,
        "available": 756,
        "housefull": 0,
        "fastfilling": 0
      },
      {
        "venue": "ini-cinemas-devchuli",
        "total_shows": 2,
        "seats": 584,
        "sold": 0,
        "reserved": 0,
        "available": 584,
        "housefull": 0,
        "fastfilling": 0
      },
      {
        "venue": "birat-cine",
        "total_shows": 2,
        "seats": 338,
        "sold": 0,
        "reserved": 0,
        "available": 338,
        "housefull": 0,
        "fastfilling": 0
      },
      {
        "venue": "pashupati-digital-cinema",
        "total_shows": 3,
        "seats": 660,
        "sold": 0,
        "reserved": 1,
        "available": 659,
        "housefull": 0,
        "fastfilling": 0
      },
      {
        "venue": "bamel-cinemas",
        "total_shows": 2,
        "seats": 274,
        "sold": 0,
        "reserved": 2,
        "available": 272,
        "housefull": 0,
        "fastfilling": 0
      }
    ]
  },
  {
    "movie_id": "zFrpNumaQ5YugBt2dcB6cQ",
    "movie_name": "They Will Kill You",
    "total_shows": 25,
    "seats": 4115,
    "sold": 31,
    "reserved": 94,
    "available": 3990,
    "housefull": 0,
    "fastfilling": 0,
    "venues": [
      {
        "venue": "ini-lotse-ktm",
        "total_shows": 1,
        "seats": 240,
        "sold": 0,
        "reserved": 0,
        "available": 240,
        "housefull": 0,
        "fastfilling": 0
      },
      {
        "venue": "ini-cinemas-nb-center",
        "total_shows": 1,
        "seats": 177,
        "sold": 0,
        "reserved": 0,
        "available": 177,
        "housefull": 0,
        "fastfilling": 0
      },
      {
        "venue": "big-movies",
        "total_shows": 1,
        "seats": 270,
        "sold": 0,
        "reserved": 50,
        "available": 220,
        "housefull": 0,
        "fastfilling": 0
      },
      {
        "venue": "fcube",
        "total_shows": 1,
        "seats": 198,
        "sold": 4,
        "reserved": 11,
        "available": 183,
        "housefull": 0,
        "fastfilling": 0
      },
      {
        "venue": "qfx-durbar",
        "total_shows": 1,
        "seats": 53,
        "sold": 0,
        "reserved": 0,
        "available": 53,
        "housefull": 0,
        "fastfilling": 0
      },
      {
        "venue": "one-cinemas-new-baneshwor",
        "total_shows": 1,
        "seats": 67,
        "sold": 6,
        "reserved": 0,
        "available": 61,
        "housefull": 0,
        "fastfilling": 0
      },
      {
        "venue": "ranjana-cineplex",
        "total_shows": 1,
        "seats": 118,
        "sold": 0,
        "reserved": 0,
        "available": 118,
        "housefull": 0,
        "fastfilling": 0
      },
      {
        "venue": "qfx-chhaya",
        "total_shows": 2,
        "seats": 224,
        "sold": 2,
        "reserved": 0,
        "available": 222,
        "housefull": 0,
        "fastfilling": 0
      },
      {
        "venue": "qfx-labim",
        "total_shows": 1,
        "seats": 182,
        "sold": 2,
        "reserved": 0,
        "available": 180,
        "housefull": 0,
        "fastfilling": 0
      },
      {
        "venue": "bsr-movies",
        "total_shows": 1,
        "seats": 180,
        "sold": 0,
        "reserved": 15,
        "available": 165,
        "housefull": 0,
        "fastfilling": 0
      },
      {
        "venue": "one-cinemas-kalimati",
        "total_shows": 1,
        "seats": 151,
        "sold": 14,
        "reserved": 0,
        "available": 137,
        "housefull": 0,
        "fastfilling": 0
      },
      {
        "venue": "qfx-square-mall",
        "total_shows": 1,
        "seats": 139,
        "sold": 0,
        "reserved": 0,
        "available": 139,
        "housefull": 0,
        "fastfilling": 0
      },
      {
        "venue": "qs-cinemas",
        "total_shows": 2,
        "seats": 311,
        "sold": 2,
        "reserved": 0,
        "available": 309,
        "housefull": 0,
        "fastfilling": 0
      },
      {
        "venue": "qfx-civil",
        "total_shows": 1,
        "seats": 259,
        "sold": 0,
        "reserved": 0,
        "available": 259,
        "housefull": 0,
        "fastfilling": 0
      },
      {
        "venue": "qfx-skyline",
        "total_shows": 1,
        "seats": 132,
        "sold": 0,
        "reserved": 0,
        "available": 132,
        "housefull": 0,
        "fastfilling": 0
      },
      {
        "venue": "qfx-jalma",
        "total_shows": 1,
        "seats": 268,
        "sold": 0,
        "reserved": 0,
        "available": 268,
        "housefull": 0,
        "fastfilling": 0
      },
      {
        "venue": "chitwan-cineplex",
        "total_shows": 1,
        "seats": 143,
        "sold": 1,
        "reserved": 0,
        "available": 142,
        "housefull": 0,
        "fastfilling": 0
      },
      {
        "venue": "qfx-bhaktapur",
        "total_shows": 1,
        "seats": 207,
        "sold": 0,
        "reserved": 0,
        "available": 207,
        "housefull": 0,
        "fastfilling": 0
      },
      {
        "venue": "ini-qbox-butwal",
        "total_shows": 1,
        "seats": 196,
        "sold": 0,
        "reserved": 0,
        "available": 196,
        "housefull": 0,
        "fastfilling": 0
      },
      {
        "venue": "pokhara-cineplex",
        "total_shows": 1,
        "seats": 231,
        "sold": 0,
        "reserved": 0,
        "available": 231,
        "housefull": 0,
        "fastfilling": 0
      },
      {
        "venue": "cdc-cinemas",
        "total_shows": 1,
        "seats": 60,
        "sold": 0,
        "reserved": 0,
        "available": 60,
        "housefull": 0,
        "fastfilling": 0
      },
      {
        "venue": "qfx-butwal",
        "total_shows": 1,
        "seats": 176,
        "sold": 0,
        "reserved": 18,
        "available": 158,
        "housefull": 0,
        "fastfilling": 0
      },
      {
        "venue": "qfx-one-stop-mall",
        "total_shows": 1,
        "seats": 133,
        "sold": 0,
        "reserved": 0,
        "available": 133,
        "housefull": 0,
        "fastfilling": 0
      }
    ]
  },
  {
    "movie_id": "aQWrEZXzxfbRCKcQhTNidH",
    "movie_name": "Project Hail Mary",
    "total_shows": 11,
    "seats": 1536,
    "sold": 90,
    "reserved": 47,
    "available": 1399,
    "housefull": 0,
    "fastfilling": 0,
    "venues": [
      {
        "venue": "big-movies",
        "total_shows": 1,
        "seats": 279,
        "sold": 0,
        "reserved": 45,
        "available": 234,
        "housefull": 0,
        "fastfilling": 0
      },
      {
        "venue": "ranjana-cineplex",
        "total_shows": 1,
        "seats": 118,
        "sold": 1,
        "reserved": 1,
        "available": 116,
        "housefull": 0,
        "fastfilling": 0
      },
      {
        "venue": "one-cinemas-new-baneshwor",
        "total_shows": 1,
        "seats": 67,
        "sold": 10,
        "reserved": 0,
        "available": 57,
        "housefull": 0,
        "fastfilling": 0
      },
      {
        "venue": "qfx-durbar",
        "total_shows": 1,
        "seats": 51,
        "sold": 0,
        "reserved": 1,
        "available": 50,
        "housefull": 0,
        "fastfilling": 0
      },
      {
        "venue": "qfx-labim",
        "total_shows": 1,
        "seats": 183,
        "sold": 54,
        "reserved": 0,
        "available": 129,
        "housefull": 0,
        "fastfilling": 0
      },
      {
        "venue": "qfx-chhaya",
        "total_shows": 2,
        "seats": 222,
        "sold": 10,
        "reserved": 0,
        "available": 212,
        "housefull": 0,
        "fastfilling": 0
      },
      {
        "venue": "bishwojyoti-cineplex",
        "total_shows": 1,
        "seats": 89,
        "sold": 2,
        "reserved": 0,
        "available": 87,
        "housefull": 0,
        "fastfilling": 0
      },
      {
        "venue": "qfx-square-mall",
        "total_shows": 1,
        "seats": 139,
        "sold": 9,
        "reserved": 0,
        "available": 130,
        "housefull": 0,
        "fastfilling": 0
      },
      {
        "venue": "qfx-civil",
        "total_shows": 1,
        "seats": 259,
        "sold": 4,
        "reserved": 0,
        "available": 255,
        "housefull": 0,
        "fastfilling": 0
      },
      {
        "venue": "qs-cinemas",
        "total_shows": 1,
        "seats": 129,
        "sold": 0,
        "reserved": 0,
        "available": 129,
        "housefull": 0,
        "fastfilling": 0
      }
    ]
  },
  {
    "movie_id": "TrAcSfZv4oSLw47hzBudCQ",
    "movie_name": "Aa Bata Aama",
    "total_shows": 1,
    "seats": 126,
    "sold": 0,
    "reserved": 0,
    "available": 126,
    "housefull": 0,
    "fastfilling": 0,
    "venues": [
      {
        "venue": "cineroyale",
        "total_shows": 1,
        "seats": 126,
        "sold": 0,
        "reserved": 0,
        "available": 126,
        "housefull": 0,
        "fastfilling": 0
      }
    ]
  },
  {
    "movie_id": "pDcmgzWp2kpArw5qa8S5w4",
    "movie_name": "Hami Teen Bhai",
    "total_shows": 33,
    "seats": 5824,
    "sold": 59,
    "reserved": 95,
    "available": 5670,
    "housefull": 0,
    "fastfilling": 0,
    "venues": [
      {
        "venue": "ini-lotse-ktm",
        "total_shows": 1,
        "seats": 240,
        "sold": 0,
        "reserved": 0,
        "available": 240,
        "housefull": 0,
        "fastfilling": 0
      },
      {
        "venue": "ini-cinemas-nb-center",
        "total_shows": 1,
        "seats": 177,
        "sold": 0,
        "reserved": 0,
        "available": 177,
        "housefull": 0,
        "fastfilling": 0
      },
      {
        "venue": "fcube",
        "total_shows": 1,
        "seats": 210,
        "sold": 5,
        "reserved": 10,
        "available": 195,
        "housefull": 0,
        "fastfilling": 0
      },
      {
        "venue": "bsr-movies",
        "total_shows": 1,
        "seats": 180,
        "sold": 0,
        "reserved": 15,
        "available": 165,
        "housefull": 0,
        "fastfilling": 0
      },
      {
        "venue": "ranjana-cineplex",
        "total_shows": 1,
        "seats": 118,
        "sold": 0,
        "reserved": 0,
        "available": 118,
        "housefull": 0,
        "fastfilling": 0
      },
      {
        "venue": "one-cinemas-new-baneshwor",
        "total_shows": 1,
        "seats": 67,
        "sold": 6,
        "reserved": 0,
        "available": 61,
        "housefull": 0,
        "fastfilling": 0
      },
      {
        "venue": "kirtipur-cineplex",
        "total_shows": 1,
        "seats": 101,
        "sold": 0,
        "reserved": 0,
        "available": 101,
        "housefull": 0,
        "fastfilling": 0
      },
      {
        "venue": "bishwojyoti-cineplex",
        "total_shows": 1,
        "seats": 89,
        "sold": 0,
        "reserved": 0,
        "available": 89,
        "housefull": 0,
        "fastfilling": 0
      },
      {
        "venue": "one-cinemas-kalimati",
        "total_shows": 1,
        "seats": 136,
        "sold": 14,
        "reserved": 0,
        "available": 122,
        "housefull": 0,
        "fastfilling": 0
      },
      {
        "venue": "qfx-square-mall",
        "total_shows": 1,
        "seats": 139,
        "sold": 5,
        "reserved": 0,
        "available": 134,
        "housefull": 0,
        "fastfilling": 0
      },
      {
        "venue": "qfx-civil",
        "total_shows": 1,
        "seats": 259,
        "sold": 5,
        "reserved": 0,
        "available": 254,
        "housefull": 0,
        "fastfilling": 0
      },
      {
        "venue": "chitwan-cineplex",
        "total_shows": 1,
        "seats": 143,
        "sold": 10,
        "reserved": 0,
        "available": 133,
        "housefull": 0,
        "fastfilling": 0
      },
      {
        "venue": "ini-simara",
        "total_shows": 1,
        "seats": 118,
        "sold": 0,
        "reserved": 0,
        "available": 118,
        "housefull": 0,
        "fastfilling": 0
      },
      {
        "venue": "ini-qbox-butwal",
        "total_shows": 1,
        "seats": 196,
        "sold": 0,
        "reserved": 0,
        "available": 196,
        "housefull": 0,
        "fastfilling": 0
      },
      {
        "venue": "qfx-jalma",
        "total_shows": 1,
        "seats": 265,
        "sold": 0,
        "reserved": 0,
        "available": 265,
        "housefull": 0,
        "fastfilling": 0
      },
      {
        "venue": "big-movies",
        "total_shows": 1,
        "seats": 270,
        "sold": 0,
        "reserved": 50,
        "available": 220,
        "housefull": 0,
        "fastfilling": 0
      },
      {
        "venue": "qfx-butwal",
        "total_shows": 1,
        "seats": 176,
        "sold": 0,
        "reserved": 18,
        "available": 158,
        "housefull": 0,
        "fastfilling": 0
      },
      {
        "venue": "qfx-bhaktapur",
        "total_shows": 1,
        "seats": 247,
        "sold": 7,
        "reserved": 2,
        "available": 238,
        "housefull": 0,
        "fastfilling": 0
      },
      {
        "venue": "pokhara-cineplex",
        "total_shows": 1,
        "seats": 231,
        "sold": 7,
        "reserved": 0,
        "available": 224,
        "housefull": 0,
        "fastfilling": 0
      },
      {
        "venue": "qfx-apex-mall",
        "total_shows": 1,
        "seats": 120,
        "sold": 0,
        "reserved": 0,
        "available": 120,
        "housefull": 0,
        "fastfilling": 0
      },
      {
        "venue": "elite-cinemas",
        "total_shows": 2,
        "seats": 286,
        "sold": 0,
        "reserved": 0,
        "available": 286,
        "housefull": 0,
        "fastfilling": 0
      },
      {
        "venue": "suvakamna-cinemas",
        "total_shows": 2,
        "seats": 380,
        "sold": 0,
        "reserved": 0,
        "available": 380,
        "housefull": 0,
        "fastfilling": 0
      },
      {
        "venue": "qfx-one-stop-mall",
        "total_shows": 1,
        "seats": 138,
        "sold": 0,
        "reserved": 0,
        "available": 138,
        "housefull": 0,
        "fastfilling": 0
      },
      {
        "venue": "qfx-cineflix-itahari",
        "total_shows": 1,
        "seats": 134,
        "sold": 0,
        "reserved": 0,
        "available": 134,
        "housefull": 0,
        "fastfilling": 0
      },
      {
        "venue": "ini-cinemas-devchuli",
        "total_shows": 1,
        "seats": 292,
        "sold": 0,
        "reserved": 0,
        "available": 292,
        "housefull": 0,
        "fastfilling": 0
      },
      {
        "venue": "qfx-bageshwori",
        "total_shows": 1,
        "seats": 288,
        "sold": 0,
        "reserved": 0,
        "available": 288,
        "housefull": 0,
        "fastfilling": 0
      },
      {
        "venue": "cdc-cinemas",
        "total_shows": 1,
        "seats": 60,
        "sold": 0,
        "reserved": 0,
        "available": 60,
        "housefull": 0,
        "fastfilling": 0
      },
      {
        "venue": "birat-cine",
        "total_shows": 1,
        "seats": 169,
        "sold": 0,
        "reserved": 0,
        "available": 169,
        "housefull": 0,
        "fastfilling": 0
      },
      {
        "venue": "pathivara-cine-plaza",
        "total_shows": 2,
        "seats": 458,
        "sold": 0,
        "reserved": 0,
        "available": 458,
        "housefull": 0,
        "fastfilling": 0
      },
      {
        "venue": "bamel-cinemas",
        "total_shows": 1,
        "seats": 137,
        "sold": 0,
        "reserved": 0,
        "available": 137,
        "housefull": 0,
        "fastfilling": 0
      }
    ]
  }
]