{
  "date": "2026-04-18",
  "lastUpdated": "04:06 AM, 18 April 2026",
  "shows": [
    {
      "movie_id": "UiB82iFPd63iHcjiGjhcXg",
      "movie_name": "Bhooth Bangla",
      "show_id": "163851:qfx-chhaya",
      "venue": null,
      "theatre": null,
      "date": "2026-04-18",
      "time": null,
      "seats": 0,
      "sold": 0,
      "reserved": 0,
      "available": 0,
      "gross": 0,
      "occupancy_percent": 0,
      "error": "401 Client Error: Unauthorized for url: https://khalti.com/api/v2/service/use/movie/showinfo-v2/",
      "skipped": true
    },
    {
      "movie_id": "UiB82iFPd63iHcjiGjhcXg",
      "movie_name": "Bhooth Bangla",
      "show_id": "164034:qfx-labim",
      "venue": null,
      "theatre": null,
      "date": "2026-04-18",
      "time": null,
      "seats": 0,
      "sold": 0,
      "reserved": 0,
      "available": 0,
      "gross": 0,
      "occupancy_percent": 0,
      "error": "401 Client Error: Unauthorized for url: https://khalti.com/api/v2/service/use/movie/showinfo-v2/",
      "skipped": true
    },
    {
      "movie_id": "UiB82iFPd63iHcjiGjhcXg",
      "movie_name": "Bhooth Bangla",
      "show_id": "163880:qfx-durbar",
      "venue": null,
      "theatre": null,
      "date": "2026-04-18",
      "time": null,
      "seats": 0,
      "sold": 0,
      "reserved": 0,
      "available": 0,
      "gross": 0,
      "occupancy_percent": 0,
      "error": "401 Client Error: Unauthorized for url: https://khalti.com/api/v2/service/use/movie/showinfo-v2/",
      "skipped": true
    },
    {
      "movie_id": "Hhu6sycBNYKXFtPeSEjvTR",
      "movie_name": "Lee Cronin's The Mummy",
      "show_id": "163948:qfx-durbar",
      "venue": null,
      "theatre": null,
      "date": "2026-04-18",
      "time": null,
      "seats": 0,
      "sold": 0,
      "reserved": 0,
      "available": 0,
      "gross": 0,
      "occupancy_percent": 0,
      "error": "401 Client Error: Unauthorized for url: https://khalti.com/api/v2/service/use/movie/showinfo-v2/",
      "skipped": true
    },
    {
      "movie_id": "zDquhoHrfUHpyVzquamLCN",
      "movie_name": "Dhurandhar - The Revenge",
      "show_id": "163834:qfx-chhaya",
      "venue": null,
      "theatre": null,
      "date": "2026-04-18",
      "time": null,
      "seats": 0,
      "sold": 0,
      "reserved": 0,
      "available": 0,
      "gross": 0,
      "occupancy_percent": 0,
      "error": "401 Client Error: Unauthorized for url: https://khalti.com/api/v2/service/use/movie/showinfo-v2/",
      "skipped": true
    }
  ]
}