{
  "date": "20260425",
  "lastUpdated": "12:39 PM, 25 April 2026",
  "movies": {
    "Sura Detuwo": {
      "totalShows": 5,
      "totalGross": 2400.0,
      "totalSold": 6,
      "totalSeats": 636,
      "formats": {
        "ET00006009": {
          "format": "2D",
          "language": "Sinhala",
          "shows": 5,
          "gross": 2400.0,
          "sold": 6,
          "totalSeats": 636,
          "fastfilling": 0,
          "housefull": 0
        }
      },
      "globalOccupancy": 0.94
    },
    "Youth": {
      "totalShows": 2,
      "totalGross": 10200.0,
      "totalSold": 12,
      "totalSeats": 235,
      "formats": {
        "ET00006019": {
          "format": "2D",
          "language": "Tamil",
          "shows": 2,
          "gross": 10200.0,
          "sold": 12,
          "totalSeats": 235,
          "fastfilling": 0,
          "housefull": 0
        }
      },
      "globalOccupancy": 5.11
    },
    "Riverstone": {
      "totalShows": 12,
      "totalGross": 91550.0,
      "totalSold": 177,
      "totalSeats": 2320,
      "formats": {
        "ET00006048": {
          "format": "2D",
          "language": "Sinhala",
          "shows": 12,
          "gross": 91550.0,
          "sold": 177,
          "totalSeats": 2320,
          "fastfilling": 0,
          "housefull": 0
        }
      },
      "globalOccupancy": 7.63
    },
    "Sergeant Punchisoma": {
      "totalShows": 9,
      "totalGross": 28400.0,
      "totalSold": 58,
      "totalSeats": 2113,
      "formats": {
        "ET00006047": {
          "format": "2D",
          "language": "Sinhala",
          "shows": 9,
          "gross": 28400.0,
          "sold": 58,
          "totalSeats": 2113,
          "fastfilling": 0,
          "housefull": 0
        }
      },
      "globalOccupancy": 2.74
    },
    "Dharmayuddhaya 2": {
      "totalShows": 22,
      "totalGross": 283500.0,
      "totalSold": 393,
      "totalSeats": 4350,
      "formats": {
        "ET00005975": {
          "format": "2D",
          "language": "Sinhala",
          "shows": 22,
          "gross": 283500.0,
          "sold": 393,
          "totalSeats": 4350,
          "fastfilling": 0,
          "housefull": 0
        }
      },
      "globalOccupancy": 9.03
    },
    "The Wife": {
      "totalShows": 8,
      "totalGross": 85450.0,
      "totalSold": 119,
      "totalSeats": 1502,
      "formats": {
        "ET00005992": {
          "format": "2D",
          "language": "Sinhala",
          "shows": 8,
          "gross": 85450.0,
          "sold": 119,
          "totalSeats": 1502,
          "fastfilling": 1,
          "housefull": 0
        }
      },
      "globalOccupancy": 7.92
    },
    "LIK: Love Insurance Kompany": {
      "totalShows": 9,
      "totalGross": 55700.0,
      "totalSold": 60,
      "totalSeats": 1652,
      "formats": {
        "ET00005927": {
          "format": "2D",
          "language": "Tamil",
          "shows": 9,
          "gross": 55700.0,
          "sold": 60,
          "totalSeats": 1652,
          "fastfilling": 0,
          "housefull": 0
        }
      },
      "globalOccupancy": 3.63
    },
    "Mr. X": {
      "totalShows": 7,
      "totalGross": 16850.0,
      "totalSold": 27,
      "totalSeats": 1236,
      "formats": {
        "ET00006049": {
          "format": "2D",
          "language": "Tamil",
          "shows": 7,
          "gross": 16850.0,
          "sold": 27,
          "totalSeats": 1236,
          "fastfilling": 0,
          "housefull": 0
        }
      },
      "globalOccupancy": 2.18
    },
    "Sivakasi": {
      "totalShows": 5,
      "totalGross": 5600.0,
      "totalSold": 14,
      "totalSeats": 1108,
      "formats": {
        "ET00006053": {
          "format": "2D",
          "language": "Tamil",
          "shows": 5,
          "gross": 5600.0,
          "sold": 14,
          "totalSeats": 1108,
          "fastfilling": 0,
          "housefull": 0
        }
      },
      "globalOccupancy": 1.26
    },
    "OIC Gadafi": {
      "totalShows": 21,
      "totalGross": 202700.0,
      "totalSold": 182,
      "totalSeats": 2883,
      "formats": {
        "ET00006051": {
          "format": "2D",
          "language": "Sinhala",
          "shows": 21,
          "gross": 202700.0,
          "sold": 182,
          "totalSeats": 2883,
          "fastfilling": 1,
          "housefull": 0
        }
      },
      "globalOccupancy": 6.31
    },
    "The Super Mario Galaxy Movie": {
      "totalShows": 5,
      "totalGross": 55800.0,
      "totalSold": 46,
      "totalSeats": 561,
      "formats": {
        "ET00006030": {
          "format": "3D",
          "language": "English",
          "shows": 5,
          "gross": 55800.0,
          "sold": 46,
          "totalSeats": 561,
          "fastfilling": 0,
          "housefull": 0
        }
      },
      "globalOccupancy": 8.2
    },
    "Lee Cronins The Mummy": {
      "totalShows": 5,
      "totalGross": 116400.0,
      "totalSold": 62,
      "totalSeats": 474,
      "formats": {
        "ET00006039": {
          "format": "2D",
          "language": "English",
          "shows": 5,
          "gross": 116400.0,
          "sold": 62,
          "totalSeats": 474,
          "fastfilling": 1,
          "housefull": 0
        }
      },
      "globalOccupancy": 13.08
    },
    "Hoppers": {
      "totalShows": 3,
      "totalGross": 102000.0,
      "totalSold": 88,
      "totalSeats": 314,
      "formats": {
        "ET00006005": {
          "format": "2D",
          "language": "English",
          "shows": 1,
          "gross": 32500.0,
          "sold": 25,
          "totalSeats": 99,
          "fastfilling": 0,
          "housefull": 0
        },
        "ET00006008": {
          "format": "3D",
          "language": "English",
          "shows": 2,
          "gross": 69500.0,
          "sold": 63,
          "totalSeats": 215,
          "fastfilling": 0,
          "housefull": 0
        }
      },
      "globalOccupancy": 28.03
    },
    "The Drama": {
      "totalShows": 1,
      "totalGross": 9600.0,
      "totalSold": 8,
      "totalSeats": 140,
      "formats": {
        "ET00006037": {
          "format": "2D",
          "language": "English",
          "shows": 1,
          "gross": 9600.0,
          "sold": 8,
          "totalSeats": 140,
          "fastfilling": 0,
          "housefull": 0
        }
      },
      "globalOccupancy": 5.71
    },
    "Michael": {
      "totalShows": 21,
      "totalGross": 1261650.0,
      "totalSold": 646,
      "totalSeats": 3691,
      "formats": {
        "ET00006006": {
          "format": "2D",
          "language": "English",
          "shows": 21,
          "gross": 1261650.0,
          "sold": 646,
          "totalSeats": 3691,
          "fastfilling": 2,
          "housefull": 0
        }
      },
      "globalOccupancy": 17.5
    },
    "Crime 101": {
      "totalShows": 1,
      "totalGross": 5200.0,
      "totalSold": 2,
      "totalSeats": 22,
      "formats": {
        "ET00005994": {
          "format": "2D",
          "language": "English",
          "shows": 1,
          "gross": 5200.0,
          "sold": 2,
          "totalSeats": 22,
          "fastfilling": 0,
          "housefull": 0
        }
      },
      "globalOccupancy": 9.09
    },
    "Dharmayudhaya": {
      "totalShows": 1,
      "totalGross": 1600.0,
      "totalSold": 2,
      "totalSeats": 134,
      "formats": {
        "ET00000157": {
          "format": "2D",
          "language": "Sinhala",
          "shows": 1,
          "gross": 1600.0,
          "sold": 2,
          "totalSeats": 134,
          "fastfilling": 0,
          "housefull": 0
        }
      },
      "globalOccupancy": 1.49
    },
    " Father": {
      "totalShows": 3,
      "totalGross": 55100.0,
      "totalSold": 47,
      "totalSeats": 435,
      "formats": {
        "ET00005963": {
          "format": "2D",
          "language": "Sinhala",
          "shows": 3,
          "gross": 55100.0,
          "sold": 47,
          "totalSeats": 435,
          "fastfilling": 0,
          "housefull": 0
        }
      },
      "globalOccupancy": 10.8
    },
    "Project Hail Mary": {
      "totalShows": 3,
      "totalGross": 172800.0,
      "totalSold": 126,
      "totalSeats": 433,
      "formats": {
        "ET00006026": {
          "format": "2D",
          "language": "English",
          "shows": 3,
          "gross": 172800.0,
          "sold": 126,
          "totalSeats": 433,
          "fastfilling": 0,
          "housefull": 0
        }
      },
      "globalOccupancy": 29.1
    }
  }
}