{
  "date": "20260306",
  "lastUpdated": "09:37 AM, 06 March 2026",
  "movies": {
    "Avatar: Fire and Ash": {
      "totalShows": 2,
      "totalGross": 7000.0,
      "totalSold": 5,
      "totalSeats": 269,
      "formats": {
        "ET00005938": {
          "format": "3D",
          "language": "English",
          "shows": 2,
          "gross": 7000.0,
          "sold": 5,
          "totalSeats": 269,
          "fastfilling": 0,
          "housefull": 0
        }
      },
      "globalOccupancy": 1.86
    },
    "Zootopia 2": {
      "totalShows": 4,
      "totalGross": 8100.0,
      "totalSold": 7,
      "totalSeats": 478,
      "formats": {
        "ET00005925": {
          "format": "2D",
          "language": "English",
          "shows": 2,
          "gross": 8100.0,
          "sold": 7,
          "totalSeats": 263,
          "fastfilling": 0,
          "housefull": 0
        },
        "ET00005930": {
          "format": "3D",
          "language": "English",
          "shows": 2,
          "gross": 0.0,
          "sold": 0,
          "totalSeats": 215,
          "fastfilling": 0,
          "housefull": 0
        }
      },
      "globalOccupancy": 1.46
    },
    " Father": {
      "totalShows": 13,
      "totalGross": 61100.0,
      "totalSold": 70,
      "totalSeats": 2412,
      "formats": {
        "ET00005963": {
          "format": "2D",
          "language": "Sinhala",
          "shows": 13,
          "gross": 61100.0,
          "sold": 70,
          "totalSeats": 2412,
          "fastfilling": 0,
          "housefull": 0
        }
      },
      "globalOccupancy": 2.9
    },
    "Hoppers": {
      "totalShows": 4,
      "totalGross": 23300.0,
      "totalSold": 19,
      "totalSeats": 452,
      "formats": {
        "ET00006008": {
          "format": "3D",
          "language": "English",
          "shows": 3,
          "gross": 13400.0,
          "sold": 10,
          "totalSeats": 312,
          "fastfilling": 0,
          "housefull": 0
        },
        "ET00006005": {
          "format": "2D",
          "language": "English",
          "shows": 1,
          "gross": 9900.0,
          "sold": 9,
          "totalSeats": 140,
          "fastfilling": 0,
          "housefull": 0
        }
      },
      "globalOccupancy": 4.2
    },
    "The Wife": {
      "totalShows": 28,
      "totalGross": 57100.0,
      "totalSold": 104,
      "totalSeats": 5471,
      "formats": {
        "ET00005992": {
          "format": "2D",
          "language": "Sinhala",
          "shows": 28,
          "gross": 57100.0,
          "sold": 104,
          "totalSeats": 5471,
          "fastfilling": 0,
          "housefull": 0
        }
      },
      "globalOccupancy": 1.9
    },
    "Scream 7": {
      "totalShows": 4,
      "totalGross": 13200.0,
      "totalSold": 11,
      "totalSeats": 379,
      "formats": {
        "ET00006002": {
          "format": "2D",
          "language": "English",
          "shows": 4,
          "gross": 13200.0,
          "sold": 11,
          "totalSeats": 379,
          "fastfilling": 0,
          "housefull": 0
        }
      },
      "globalOccupancy": 2.9
    },
    "Wuthering Heights": {
      "totalShows": 2,
      "totalGross": 11600.0,
      "totalSold": 6,
      "totalSeats": 240,
      "formats": {
        "ET00005997": {
          "format": "2D",
          "language": "English",
          "shows": 2,
          "gross": 11600.0,
          "sold": 6,
          "totalSeats": 240,
          "fastfilling": 0,
          "housefull": 0
        }
      },
      "globalOccupancy": 2.5
    },
    "Thaai Kizhavi": {
      "totalShows": 5,
      "totalGross": 5600.0,
      "totalSold": 7,
      "totalSeats": 1009,
      "formats": {
        "ET00006000": {
          "format": "2D",
          "language": "Tamil",
          "shows": 5,
          "gross": 5600.0,
          "sold": 7,
          "totalSeats": 1009,
          "fastfilling": 0,
          "housefull": 0
        }
      },
      "globalOccupancy": 0.69
    },
    "With Love": {
      "totalShows": 1,
      "totalGross": 0.0,
      "totalSold": 0,
      "totalSeats": 184,
      "formats": {
        "ET00005991": {
          "format": "2D",
          "language": "Tamil",
          "shows": 1,
          "gross": 0.0,
          "sold": 0,
          "totalSeats": 184,
          "fastfilling": 0,
          "housefull": 0
        }
      },
      "globalOccupancy": 0.0
    },
    "The Bride": {
      "totalShows": 2,
      "totalGross": 3500.0,
      "totalSold": 1,
      "totalSeats": 457,
      "formats": {
        "ET00006004": {
          "format": "2D",
          "language": "English",
          "shows": 2,
          "gross": 3500.0,
          "sold": 1,
          "totalSeats": 457,
          "fastfilling": 0,
          "housefull": 0
        }
      },
      "globalOccupancy": 0.22
    },
    "Dharmayuddhaya 2": {
      "totalShows": 22,
      "totalGross": 47500.0,
      "totalSold": 91,
      "totalSeats": 4834,
      "formats": {
        "ET00005975": {
          "format": "2D",
          "language": "Sinhala",
          "shows": 22,
          "gross": 47500.0,
          "sold": 91,
          "totalSeats": 4834,
          "fastfilling": 0,
          "housefull": 0
        }
      },
      "globalOccupancy": 1.88
    },
    "Malaki Duwe Numba": {
      "totalShows": 5,
      "totalGross": 7000.0,
      "totalSold": 20,
      "totalSeats": 1180,
      "formats": {
        "ET00005955": {
          "format": "2D",
          "language": "Sinhala",
          "shows": 5,
          "gross": 7000.0,
          "sold": 20,
          "totalSeats": 1180,
          "fastfilling": 0,
          "housefull": 0
        }
      },
      "globalOccupancy": 1.69
    },
    "The Housemaid": {
      "totalShows": 1,
      "totalGross": 0.0,
      "totalSold": 0,
      "totalSeats": 22,
      "formats": {
        "ET00005954": {
          "format": "2D",
          "language": "English",
          "shows": 1,
          "gross": 0.0,
          "sold": 0,
          "totalSeats": 22,
          "fastfilling": 0,
          "housefull": 0
        }
      },
      "globalOccupancy": 0.0
    }
  }
}